aimagic/__init__.py
aimagic/_modidx.py
aimagic/core.py
aimagic/sysp.txt
aimagic-0.1.0.data/data/etc/jupyter/nbconfig/notebook.d/nbmeta.json
aimagic-0.1.0.data/data/share/jupyter/nbextensions/nbmeta.js
aimagic-0.1.0.dist-info/licenses/LICENSE
aimagic-0.1.0.dist-info/METADATA
aimagic-0.1.0.dist-info/WHEEL
aimagic-0.1.0.dist-info/entry_points.txt
aimagic-0.1.0.dist-info/top_level.txt
aimagic-0.1.0.dist-info/RECORD
