Metadata-Version: 2.4
Name: aimagic
Version: 0.1.0
Summary: AI magic
Home-page: https://github.com/answerdotai/aimagic
Author: Jeremy Howard
Author-email: info@answer.ai
License: GNU General Public License v3 (GPLv3)
Keywords: nbdev jupyter notebook python
Classifier: Development Status :: 4 - Beta
Classifier: Intended Audience :: Developers
Classifier: License :: OSI Approved :: GNU General Public License v3 (GPLv3)
Classifier: Natural Language :: English
Classifier: Programming Language :: Python :: 3.10
Classifier: Programming Language :: Python :: 3.11
Classifier: Programming Language :: Python :: 3.12
Classifier: Programming Language :: Python :: 3.13
Classifier: Programming Language :: Python :: 3.14
Requires-Python: >=3.10
License-File: LICENSE
Requires-Dist: pip
Requires-Dist: packaging
Requires-Dist: fastcore
Requires-Dist: lisette>=0.0.28
Requires-Dist: execnb
Provides-Extra: dev
Dynamic: author
Dynamic: author-email
Dynamic: classifier
Dynamic: description
Dynamic: description-content-type
Dynamic: home-page
Dynamic: keywords
Dynamic: license
Dynamic: license-file
Dynamic: provides-extra
Dynamic: requires-dist
Dynamic: requires-python
Dynamic: summary
